[
  {
    "timestamp": "2025-09-25T06:23:26.578650",
    "message": "Screen poked"
  },
  {
    "timestamp": "2025-09-25T06:25:06.584693",
    "message": "Screen poked"
  },
  {
    "timestamp": "2025-09-25T06:26:46.591655",
    "message": "Screen poked"
  },
  {
    "timestamp": "2025-09-25T06:28:26.592683",
    "message": "Screen poked"
  },
  {
    "timestamp": "2025-09-25T06:30:06.598558",
    "message": "Screen poked"
  },
  {
    "timestamp": "2025-09-25T06:31:46.603618",
    "message": "Screen poked"
  },
  {
    "timestamp": "2025-09-25T06:33:26.608755",
    "message": "Screen poked"
  },
  {
    "timestamp": "2025-09-25T06:35:06.615485",
    "message": "Screen poked"
  },
  {
    "timestamp": "2025-09-25T06:36:46.621906",
    "message": "Screen poked"
  },
  {
    "timestamp": "2025-09-25T06:38:26.636267",
    "message": "Screen poked"
  },
  {
    "timestamp": "2025-09-25T06:40:06.641925",
    "message": "Screen poked"
  },
  {
    "timestamp": "2025-09-25T06:41:46.649513",
    "message": "Screen poked"
  },
  {
    "timestamp": "2025-09-25T06:43:26.660387",
    "message": "Screen poked"
  },
  {
    "timestamp": "2025-09-25T06:45:06.671474",
    "message": "Screen poked"
  },
  {
    "timestamp": "2025-09-25T06:46:46.684967",
    "message": "Screen poked"
  },
  {
    "timestamp": "2025-09-25T06:48:26.692777",
    "message": "Screen poked"
  },
  {
    "timestamp": "2025-09-25T06:50:06.700364",
    "message": "Screen poked"
  },
  {
    "timestamp": "2025-09-25T06:51:46.711668",
    "message": "Screen poked"
  },
  {
    "timestamp": "2025-09-25T06:53:26.721395",
    "message": "Screen poked"
  },
  {
    "timestamp": "2025-09-25T06:55:06.728519",
    "message": "Screen poked"
  },
  {
    "timestamp": "2025-09-25T06:56:46.735108",
    "message": "Screen poked"
  },
  {
    "timestamp": "2025-09-25T06:58:26.748384",
    "message": "Screen poked"
  },
  {
    "timestamp": "2025-09-25T07:00:06.760185",
    "message": "Screen poked"
  },
  {
    "timestamp": "2025-09-25T07:01:46.790862",
    "message": "Screen poked"
  },
  {
    "timestamp": "2025-09-25T07:03:26.796044",
    "message": "Screen poked"
  },
  {
    "timestamp": "2025-09-25T07:05:06.798502",
    "message": "Screen poked"
  },
  {
    "timestamp": "2025-09-25T07:06:46.809277",
    "message": "Screen poked"
  },
  {
    "timestamp": "2025-09-25T07:08:26.811573",
    "message": "Screen poked"
  },
  {
    "timestamp": "2025-09-25T07:10:06.814836",
    "message": "Screen poked"
  },
  {
    "timestamp": "2025-09-25T07:11:46.817704",
    "message": "Screen poked"
  },
  {
    "timestamp": "2025-09-25T07:13:26.820154",
    "message": "Screen poked"
  },
  {
    "timestamp": "2025-09-25T07:15:06.822736",
    "message": "Screen poked"
  },
  {
    "timestamp": "2025-09-25T07:16:46.826448",
    "message": "Screen poked"
  },
  {
    "timestamp": "2025-09-25T07:18:26.828124",
    "message": "Screen poked"
  },
  {
    "timestamp": "2025-09-25T07:20:06.830161",
    "message": "Screen poked"
  },
  {
    "timestamp": "2025-09-25T07:21:46.845637",
    "message": "Purged records older than 1 hour"
  },
  {
    "timestamp": "2025-09-25T07:21:46.857185",
    "message": "Screen poked"
  },
  {
    "timestamp": "2025-09-25T07:23:26.858227",
    "message": "Screen poked"
  },
  {
    "timestamp": "2025-09-25T07:25:06.859304",
    "message": "Screen poked"
  },
  {
    "timestamp": "2025-09-25T07:26:46.889145",
    "message": "Screen poked"
  },
  {
    "timestamp": "2025-09-25T07:28:26.892959",
    "message": "Screen poked"
  },
  {
    "timestamp": "2025-09-25T07:30:06.903122",
    "message": "Screen poked"
  }
]
